{
  "users": [
    {
      "name": "Antonette",
      "id": 1
    },
    {
      "name": "Misty",
      "id": 2
    },
    {
      "name": "Constance",
      "id": 3
    }
  ],
  "albums": [
    {
      "userId": 1,
      "title": "Handcrafted Concrete Salad",
      "id": 2
    },
    {
      "userId": 2,
      "title": "Licensed Wooden Fish",
      "id": 3
    },
    {
      "userId": 3,
      "title": "Bespoke Cotton Chicken",
      "id": 4
    }
  ],
  "photos": [
    {
      "albumid": 14,
      "url": "https://avatars.githubusercontent.com/u/24099924",
      "id": 1
    },
    {
      "albumid": 14,
      "url": "https://cloudflare-ipfs.com/ipfs/Qmd3W5DuhgHirLHGVixi6V76LhCkZUz6pnFt5AJBiyvHye/avatar/1169.jpg",
      "id": 2
    },
    {
      "albumid": 14,
      "url": "https://avatars.githubusercontent.com/u/92668154",
      "id": 3
    },
    {
      "albumid": 14,
      "url": "https://avatars.githubusercontent.com/u/60463812",
      "id": 4
    },
    {
      "albumid": 14,
      "url": "https://cloudflare-ipfs.com/ipfs/Qmd3W5DuhgHirLHGVixi6V76LhCkZUz6pnFt5AJBiyvHye/avatar/412.jpg",
      "id": 5
    },
    {
      "albumid": 14,
      "url": "https://cloudflare-ipfs.com/ipfs/Qmd3W5DuhgHirLHGVixi6V76LhCkZUz6pnFt5AJBiyvHye/avatar/179.jpg",
      "id": 6
    },
    {
      "albumid": 3,
      "url": "https://avatars.githubusercontent.com/u/68440859",
      "id": 7
    },
    {
      "albumid": 3,
      "url": "https://avatars.githubusercontent.com/u/23149697",
      "id": 8
    },
    {
      "albumid": 3,
      "url": "https://avatars.githubusercontent.com/u/11527085",
      "id": 9
    },
    {
      "albumid": 2,
      "url": "https://cloudflare-ipfs.com/ipfs/Qmd3W5DuhgHirLHGVixi6V76LhCkZUz6pnFt5AJBiyvHye/avatar/331.jpg",
      "id": 10
    },
    {
      "albumid": 1,
      "url": "https://cloudflare-ipfs.com/ipfs/Qmd3W5DuhgHirLHGVixi6V76LhCkZUz6pnFt5AJBiyvHye/avatar/1163.jpg",
      "id": 11
    },
    {
      "albumid": 1,
      "url": "https://avatars.githubusercontent.com/u/29554024",
      "id": 12
    },
    {
      "albumid": 2,
      "url": "https://cloudflare-ipfs.com/ipfs/Qmd3W5DuhgHirLHGVixi6V76LhCkZUz6pnFt5AJBiyvHye/avatar/652.jpg",
      "id": 13
    },
    {
      "albumid": 2,
      "url": "https://avatars.githubusercontent.com/u/10185109",
      "id": 14
    }
  ]
}